chkptai/ChkptAI.py
chkptai/__init__.py
chkptai/chkpt_types.py
chkptai-0.1.3.dist-info/METADATA
chkptai-0.1.3.dist-info/WHEEL
chkptai-0.1.3.dist-info/top_level.txt
chkptai-0.1.3.dist-info/RECORD
